json_relational/__init__.py
json_relational/debug.py
json_relational/src/__init__.py
json_relational/src/flatten_strategies.py
json_relational/src/main.py
json_relational/src/models.py
json_relational/src/protocols.py
json_relational-0.0.3.dist-info/METADATA
json_relational-0.0.3.dist-info/WHEEL
json_relational-0.0.3.dist-info/top_level.txt
json_relational-0.0.3.dist-info/RECORD
