Metadata-Version: 2.1
Name: json-relational
Version: 0.0.3
Summary: convert nested json to flat objects and their mapping
Home-page: https://github.com/gr0vity-dev/json-relational
Author: gr0vity
